qubit_discovery/__init__.py
qubit_discovery/_version.py
qubit_discovery/losses/__init__.py
qubit_discovery/losses/functions.py
qubit_discovery/losses/loss.py
qubit_discovery/losses/utils.py
qubit_discovery/optim/BFGS.py
qubit_discovery/optim/SGD.py
qubit_discovery/optim/__init__.py
qubit_discovery/optim/exceptions.py
qubit_discovery/optim/optim.py
qubit_discovery/optim/reparameterization.py
qubit_discovery/optim/sampler.py
qubit_discovery/optim/truncation.py
qubit_discovery/optim/utils.py
qubit_discovery/tests/__init__.py
qubit_discovery/tests/conftest.py
qubit_discovery/tests/test_BFGS.py
qubit_discovery/tests/test_SGD.py
qubit_discovery/tests/test_functions.py
qubit_discovery/tests/test_functions_grad.py
qubit_discovery/tests/test_sampler.py
qubit_discovery/tests/test_truncation.py
qubit_discovery-1.0.0.dist-info/LICENSE
qubit_discovery-1.0.0.dist-info/METADATA
qubit_discovery-1.0.0.dist-info/WHEEL
qubit_discovery-1.0.0.dist-info/top_level.txt
qubit_discovery-1.0.0.dist-info/RECORD
