Metadata-Version: 2.1
Name: qubit-discovery
Version: 1.0.0
Summary: Tools to optimize superconducting circuits using SQcircuit.
Author-email: Taha Rajabzadeh <tahar@stanford.edu>, Alex Boulton-McKeehan <mckeehan@stanford.edu>, Sam Bonkowsky <sbonkov@ucsb.edu>, Amir Safavi-Naeini <safavi@stanford.edu>
License: BSD 3-Clause License
Project-URL: Homepage, https://github.com/stanfordLINQS/Qubit-Discovery
Keywords: superconducting circuits,superconducting qubits,machine learning,pytorch
Classifier: Development Status :: 4 - Beta
Classifier: Intended Audience :: Science/Research
Classifier: Topic :: Scientific/Engineering
Classifier: Topic :: Scientific/Engineering :: Physics
Classifier: License :: OSI Approved :: BSD License
Classifier: Programming Language :: Python :: 3
Classifier: Operating System :: OS Independent
Requires-Python: >=3.9
License-File: LICENSE
Requires-Dist: numpy >=1.23
Requires-Dist: torch >=2.0
Requires-Dist: scipy >=1.10
Requires-Dist: SQcircuit >=1.0.0
Requires-Dist: dill ==0.3.8
Requires-Dist: matplotlib >=3.7.2
Requires-Dist: tqdm >=4.60.0
Provides-Extra: scripts
Requires-Dist: docopt ; extra == 'scripts'
Requires-Dist: pyyaml ; extra == 'scripts'
Provides-Extra: tests
Requires-Dist: pytest >7.4 ; extra == 'tests'
